gias3.common-3.0.0-py3.9-nspkg.pth
gias3/common/__init__.py
gias3/common/geoprimitives.py
gias3/common/math.py
gias3/common/misc.py
gias3/common/tabledata.py
gias3/common/transform3D.py
gias3.common-3.0.0.dist-info/LICENSE
gias3.common-3.0.0.dist-info/METADATA
gias3.common-3.0.0.dist-info/WHEEL
gias3.common-3.0.0.dist-info/namespace_packages.txt
gias3.common-3.0.0.dist-info/top_level.txt
gias3.common-3.0.0.dist-info/RECORD
